README.txt
setup.cfg
setup.py
test_decorators.py
DecoratorTools.egg-info/PKG-INFO
DecoratorTools.egg-info/SOURCES.txt
DecoratorTools.egg-info/dependency_links.txt
DecoratorTools.egg-info/namespace_packages.txt
DecoratorTools.egg-info/top_level.txt
ez_setup/README.txt
ez_setup/__init__.py
peak/__init__.py
peak/util/__init__.py
peak/util/decorators.py