Metadata-Version: 1.0
Name: DecoratorTools
Version: 1.6
Summary: Class, function, and metaclass decorators -- even in Python 2.3 (now with source debugging for generated code)!
Home-page: http://cheeseshop.python.org/pypi/DecoratorTools
Author: Phillip J. Eby
Author-email: peak@eby-sarna.com
License: PSF or ZPL
Platform: UNKNOWN
